hashtokenizers.py
hashtokenizers-0.1.3.dist-info/METADATA
hashtokenizers-0.1.3.dist-info/WHEEL
hashtokenizers-0.1.3.dist-info/top_level.txt
hashtokenizers-0.1.3.dist-info/RECORD
