Metadata-Version: 2.4
Name: hashtokenizers
Version: 0.1.3
Summary: Wrapper for tokenizers that includes hash ids
Author-email: Kevin Staight <kstaight@gmail.com>
License: MIT
Requires-Python: >=3.7
Requires-Dist: tokenizers
Requires-Dist: jump-consistent-hash
